biocodelib/__init__.py
biocodelib/deep_learning_utils.py
biocodelib/evaluation.py
biocodelib/preprocessing.py
biocodelib/utils.py
biocodelib/algorithms/__init__.py
biocodelib/algorithms/biohashing.py
biocodelib/algorithms/deep_learning.py
biocodelib/algorithms/encryption_utils.py
biocodelib/algorithms/iom_hashing.py
biocodelib/algorithms/xor_encryption.py
biocodelib/feature_extraction/__init__.py
biocodelib/feature_extraction/feature_utils.py
biocodelib/feature_extraction/image_features.py
biocodelib/feature_extraction/minutiae_extraction.py
biocodelib-0.1.0.dist-info/LICENSE
biocodelib-0.1.0.dist-info/METADATA
biocodelib-0.1.0.dist-info/WHEEL
biocodelib-0.1.0.dist-info/top_level.txt
biocodelib-0.1.0.dist-info/RECORD
