Metadata-Version: 2.1
Name: biocodelib
Version: 0.1.0
Summary: A unified Python library for converting biometric images to secure codes using classical algorithms
Home-page: https://github.com/nimajz/BiocodeLib
Author: Nima jzzz
Author-email: Nima jzzz <nimajaberzadeh@gmail.com>
License: MIT
Project-URL: Homepage, https://github.com/nimajz/BiocodeLib
Project-URL: Documentation, https://github.com/nimajz/BiocodeLib#readme
Project-URL: Repository, https://github.com/nimajz/BiocodeLib
Project-URL: Issues, https://github.com/nimajz/BiocodeLib/issues
Keywords: biometric,fingerprint,hashing,encryption,biohashing,iom-hashing,security
Classifier: Development Status :: 3 - Alpha
Classifier: Intended Audience :: Developers
Classifier: Intended Audience :: Science/Research
Classifier: License :: OSI Approved :: MIT License
Classifier: Programming Language :: Python :: 3
Classifier: Programming Language :: Python :: 3.7
Classifier: Programming Language :: Python :: 3.8
Classifier: Programming Language :: Python :: 3.9
Classifier: Programming Language :: Python :: 3.10
Classifier: Programming Language :: Python :: 3.11
Classifier: Topic :: Security
Classifier: Topic :: Scientific/Engineering :: Image Processing
Requires-Python: >=3.7
License-File: LICENSE
Requires-Dist: numpy
Requires-Dist: opencv-python
Requires-Dist: scikit-image
Requires-Dist: scipy
